HapooDB/HapooDB.py
HapooDB/__init__.py
HapooDB-1.1.2.dist-info/LICENSE.txt
HapooDB-1.1.2.dist-info/METADATA
HapooDB-1.1.2.dist-info/WHEEL
HapooDB-1.1.2.dist-info/top_level.txt
HapooDB-1.1.2.dist-info/RECORD
