Metadata-Version: 2.1
Name: HapooDB
Version: 1.1.2
Summary: Hapoo DB
Author: HapooIsLuv (Pro gamer!1!)
Author-email: <Hapoo@gmail.com>
Keywords: python,DB,Noob
Classifier: Development Status :: 1 - Planning
Classifier: Intended Audience :: Developers
Classifier: Programming Language :: Python :: 3
Classifier: Operating System :: Unix
Classifier: Operating System :: MacOS :: MacOS X
Classifier: Operating System :: Microsoft :: Windows
License-File: LICENSE.txt
